todopkg/__init__.py
todopkg/__main__.py
todopkg/todopkg.py
todopkg-1.0.7.dist-info/LICENSE
todopkg-1.0.7.dist-info/METADATA
todopkg-1.0.7.dist-info/WHEEL
todopkg-1.0.7.dist-info/top_level.txt
todopkg-1.0.7.dist-info/RECORD
