Metadata-Version: 2.1
Name: todopkg
Version: 1.0.7
Summary: A To-Do List manager package for managing your tasks efficiently.
Author-email: isomorphism1337 group <jw6699@nyu.edu>
Project-URL: homepage, https://github.com/software-students-fall2023/3-python-package-exercise-isomorphism1337.git
Keywords: todo,list,project management
Classifier: Programming Language :: Python :: 3
License-File: LICENSE
Requires-Dist: tabulate
